<vserverTable>
	<name>Get NetScaler VIRTUAL SERVERS stats</name>
	<description>Queries a NetScaler for all VIRTUAL SERVERS stats (vserverTable)</description>
	<oid_index>.1.3.6.1.4.1.5951.4.1.3.1.1.59</oid_index>
	<oid_index_parse>OID/REGEXP:^.*\.5951\.[0-9]{1,3}\.[0-9]{1,3}\.[0-9]{1,3}\.[0-9]{1,3}\.[0-9]{1,3}\.[0-9]{1,3}\.(.*)</oid_index_parse>
	<fields>
    <vsvrFullName>
			<name>vsvrFullName</name>
			<method>walk</method>
			<source>value</source>
			<direction>input</direction>
			<oid>.1.3.6.1.4.1.5951.4.1.3.1.1.59</oid>
		</vsvrFullName>
		<vsvrIPAddress>
			<name>vsvrIPAddress</name>
			<method>walk</method>
			<source>value</source>
			<direction>input</direction>
			<oid>.1.3.6.1.4.1.5951.4.1.3.1.1.2</oid>
		</vsvrIPAddress>
		<vsvrPort>
			<name>vsvrPort</name>
			<method>walk</method>
			<source>value</source>
			<direction>input</direction>
			<oid>.1.3.6.1.4.1.5951.4.1.3.1.1.3</oid>
		</vsvrPort>
		<vsvrCurClntConnections>
			<name>vsvrCurClntConnections</name>
			<method>walk</method>
			<source>value</source>
			<direction>output</direction>
			<oid>.1.3.6.1.4.1.5951.4.1.3.1.1.7</oid>
		</vsvrCurClntConnections>
		<vsvrCurSrvrConnections>
      <name>vsvrCurSrvrConnections</name>
      <method>walk</method>
      <source>value</source>
      <direction>output</direction>
      <oid>.1.3.6.1.4.1.5951.4.1.3.1.1.8</oid>
    </vsvrCurSrvrConnections>
		<vsvrTotalRequests>
      <name>vsvrTotalRequests</name>
      <method>walk</method>
      <source>value</source>
      <direction>output</direction>
      <oid>.1.3.6.1.4.1.5951.4.1.3.1.1.30</oid>
    </vsvrTotalRequests>
    <vsvrTotalRequestBytes>
      <name>vsvrTotalRequestBytes</name>
      <method>walk</method>
      <source>value</source>
      <direction>output</direction>
      <oid>.1.3.6.1.4.1.5951.4.1.3.1.1.31</oid>
    </vsvrTotalRequestBytes>
    <vsvrTotalResponses>
      <name>vsvrTotalResponses</name>
      <method>walk</method>
      <source>value</source>
      <direction>output</direction>
      <oid>.1.3.6.1.4.1.5951.4.1.3.1.1.32</oid>
    </vsvrTotalResponses>
    <vsvrTotalResponseBytes>
      <name>vsvrTotalResponseBytes</name>
      <method>walk</method>
      <source>value</source>
      <direction>output</direction>
      <oid>.1.3.6.1.4.1.5951.4.1.3.1.1.33</oid>
    </vsvrTotalResponseBytes>
    <vsvrTotalPktsRecvd>
      <name>vsvrTotalPktsRecvd</name>
      <method>walk</method>
      <source>value</source>
      <direction>output</direction>
      <oid>.1.3.6.1.4.1.5951.4.1.3.1.1.34</oid>
    </vsvrTotalPktsRecvd>
    <vsvrTotalPktsSent>
      <name>vsvrTotalPktsSent</name>
      <method>walk</method>
      <source>value</source>
      <direction>output</direction>
      <oid>.1.3.6.1.4.1.5951.4.1.3.1.1.35</oid>
    </vsvrTotalPktsSent>
    <vsvrTotalSynsRecvd>
      <name>vsvrTotalSynsRecvd</name>
      <method>walk</method>
      <source>value</source>
      <direction>output</direction>
      <oid>.1.3.6.1.4.1.5951.4.1.3.1.1.36</oid>
    </vsvrTotalSynsRecvd>
    <vsvrCurServicesDown>
      <name>vsvrCurServicesDown</name>
      <method>walk</method>
      <source>value</source>
      <direction>output</direction>
      <oid>.1.3.6.1.4.1.5951.4.1.3.1.1.37</oid>
    </vsvrCurServicesDown>
    <vsvrCurServicesUnKnown>
      <name>vsvrCurServicesUnKnown</name>
      <method>walk</method>
      <source>value</source>
      <direction>output</direction>
      <oid>.1.3.6.1.4.1.5951.4.1.3.1.1.38</oid>
    </vsvrCurServicesUnKnown>
    <vsvrCurServicesOutOfSvc>
      <name>vsvrCurServicesOutOfSvc</name>
      <method>walk</method>
      <source>value</source>
      <direction>output</direction>
      <oid>.1.3.6.1.4.1.5951.4.1.3.1.1.39</oid>
    </vsvrCurServicesOutOfSvc>
    <vsvrCurServicesTransToOutOfSvc>
      <name>vsvrCurServicesTransToOutOfSvc</name>
      <method>walk</method>
      <source>value</source>
      <direction>output</direction>
      <oid>.1.3.6.1.4.1.5951.4.1.3.1.1.40</oid>
    </vsvrCurServicesTransToOutOfSvc>
    <vsvrCurServicesUp>
      <name>vsvrCurServicesUp</name>
      <method>walk</method>
      <source>value</source>
      <direction>output</direction>
      <oid>.1.3.6.1.4.1.5951.4.1.3.1.1.41</oid>
    </vsvrCurServicesUp>
    <vsvrTotMiss>
      <name>vsvrTotMiss</name>
      <method>walk</method>
      <source>value</source>
      <direction>output</direction>
      <oid>.1.3.6.1.4.1.5951.4.1.3.1.1.42</oid>
    </vsvrTotMiss>
    <vsvrTotHits>
      <name>vsvrTotHits</name>
      <method>walk</method>
      <source>value</source>
      <direction>output</direction>
      <oid>.1.3.6.1.4.1.5951.4.1.3.1.1.48</oid>
    </vsvrTotHits>
    <vsvrTotSpillOvers>
      <name>vsvrTotSpillOvers</name>
      <method>walk</method>
      <source>value</source>
      <direction>output</direction>
      <oid>.1.3.6.1.4.1.5951.4.1.3.1.1.54</oid>
    </vsvrTotSpillOvers>
    <vsvrTotalClients>
      <name>vsvrTotalClients</name>
      <method>walk</method>
      <source>value</source>
      <direction>output</direction>
      <oid>.1.3.6.1.4.1.5951.4.1.3.1.1.56</oid>
    </vsvrTotalClients>
    <vsvrCurSslVpnUsers>
      <name>vsvrCurSslVpnUsers</name>
      <method>walk</method>
      <source>value</source>
      <direction>output</direction>
      <oid>.1.3.6.1.4.1.5951.4.1.3.1.1.60</oid>
    </vsvrCurSslVpnUsers>
    <vsvrTotalServicesBound>
      <name>vsvrTotalServicesBound</name>
      <method>walk</method>
      <source>value</source>
      <direction>output</direction>
      <oid>.1.3.6.1.4.1.5951.4.1.3.1.1.61</oid>
    </vsvrTotalServicesBound>
    <vsvrHealth>
      <name>vsvrHealth</name>
      <method>walk</method>
      <source>value</source>
      <direction>output</direction>
      <oid>.1.3.6.1.4.1.5951.4.1.3.1.1.62</oid>
    </vsvrHealth>
    <vsvrTicksSinceLastStateChange>
      <name>vsvrTicksSinceLastStateChange</name>
      <method>walk</method>
      <source>value</source>
      <direction>output</direction>
      <oid>.1.3.6.1.4.1.5951.4.1.3.1.1.63</oid>
    </vsvrTicksSinceLastStateChange>
    <vsvrTotalServers>
      <name>vsvrTotalServers</name>
      <method>walk</method>
      <source>value</source>
      <direction>output</direction>
      <oid>.1.3.6.1.4.1.5951.4.1.3.1.1.65</oid>
    </vsvrTotalServers>
    <vsvrInvalidRequestResponse>
      <name>vsvrInvalidRequestResponse</name>
      <method>walk</method>
      <source>value</source>
      <direction>output</direction>
      <oid>.1.3.6.1.4.1.5951.4.1.3.1.1.67</oid>
    </vsvrInvalidRequestResponse>
    <vsvrInvalidRequestResponseDropped>
      <name>vsvrInvalidRequestResponseDropped</name>
      <method>walk</method>
      <source>value</source>
      <direction>output</direction>
      <oid>.1.3.6.1.4.1.5951.4.1.3.1.1.68</oid>
    </vsvrInvalidRequestResponseDropped>
	</fields>
</vserverTable>
